README.md
setup.py
saturn/__init__.py
saturn/__main__.py
saturn/dispatcher.py
saturn/engine.py
saturn/state.py
saturn/version.py
saturn/auth/__init__.py
saturn/auth/dict/__init__.py
saturn/auth/dict/core.py
saturn/auth/gssapi/__init__.py
saturn/auth/none/__init__.py
saturn/auth/none/core.py
saturn/protocol/__init__.py
saturn/protocol/client_tcp.py
saturn/protocol/server_tcp.py
saturn/protocol/socks_tcp.py
saturn/protocol/socks_udp.py
saturn/protocol/connection_result/__init__.py
saturn/protocol/connection_result/address_not_supported.py
saturn/protocol/connection_result/base.py
saturn/protocol/connection_result/command_not_supported.py
saturn/protocol/connection_result/connection_refused.py
saturn/protocol/connection_result/host_unreachable.py
saturn/protocol/connection_result/network_unreachable.py
saturn/protocol/connection_result/not_allowed.py
saturn/protocol/connection_result/succeeded.py
saturn/protocol/connection_result/ttl_expired.py
saturn/socks/__init__.py
saturn/socks/authenticate.py
saturn/socks/hello.py
saturn/socks/reply.py
saturn/socks/request/__init__.py
saturn/socks/request/base.py
saturn/socks/request/bind.py
saturn/socks/request/connect.py
saturn/socks/request/udp_associate.py
saturn_proxy_server.egg-info/PKG-INFO
saturn_proxy_server.egg-info/SOURCES.txt
saturn_proxy_server.egg-info/dependency_links.txt
saturn_proxy_server.egg-info/top_level.txt