Metadata-Version: 2.1
Name: saturn-proxy-server
Version: 0.9
Summary: Socks5 async proxy server
Home-page: https://git.best-service.online/yurzs/saturn
Author: Yury (Yurzs)
Author-email: dev@best-service.online
License: MIT
Keywords: Saturn,Socks5,proxy
Platform: UNKNOWN
Classifier: Development Status :: 3 - Alpha
Classifier: Intended Audience :: Developers
Classifier: Topic :: Software Development :: Build Tools
Classifier: License :: OSI Approved :: MIT License
Classifier: Programming Language :: Python :: 3
Classifier: Programming Language :: Python :: 3.7
